Workbook

Sheet EÜR 2021 (Überarb.)
A5: Hartmut Ahting, Steuerberater, Heerstrasse 50, 60488 Frankfurt
A7: Herr | E7: Rg-Datum: | G7: 45405
A8: Roger Detroy | E8: Kunden-Nr.: | H8: 60431
A9: Heerstraße 60 | E9: Rg-Nr.: | G9: 60431-2024-001
E10: Leistungsdatum: | G10: =+G7 -> 45405
A11: 60488 Frankfurt | E11: IBAN: | F11: DE13 50070024 0 4092862 00
E12: BIC: | F12: DEUTDEDBFRA
A18: Rechnung über Honorare
A21: Für die nachfolgend aufgeführten Leistungen erlaube ich mir, nach der Steuerberatervergütungs-
A22: verordnung wie folgt abzurechnen:
A23: Leistung | E23: Wert/ | F23: Tabelle | G23: Geb.-Satz/ | H23: Gebühr
A24: §§ | E24: Std.-Satz | G24: Stunden
A25: 24 | B25: Einkommensteuererklärung ohne Ermittlung | E25: 60596 | F25: A | G25: 0,5/10 | H25: =0.5/10*1320 -> 66
B26: der einzelnen Einkünfte für | C26: 2021
B27: (Überarbeitung)
A29: 24 | B29: Gewerbesteuererklärung (Überarberitung) | C29: 2021 | E29: 32730.58 | F29: A | G29: 0.1 | H29: =+G29*977 -> 97.7
A31: 25 | B31: Einnahmenüberschußrechnung | C31: 2021 | E31: 140239.27 | F31: B | G31: 0.6 | H31: =+G31*444 -> 266.4
B32: (Überarbeitung)
A34: 16 | B34: Auslagenersatz für Post- und | E34: =SUM(H25:H31)*0.12 -> 51.612 | H34: 0
B35: Telekommunikation
E36: Gesamt | H36: =SUM(H25:H35) -> 430.1
E37: USt 19% | H37: =+H36*0.19 -> 81.719
E38: Rechnungsendbetrag | H38: =SUM(H36:H37) -> 511.819
A40: Bitte überweisen Sie den Rechnungsbetrag ohne Abzüge auf das angegebene Konto.
A49: Steuernummer: 012 801 35159

Sheet EÜR 2022
A5: Hartmut Ahting, Steuerberater, Heerstrasse 50, 60488 Frankfurt
A7: Herr | E7: Rg-Datum: | G7: 45420
A8: Roger Detroy | E8: Kunden-Nr.: | H8: 60431
A9: Heerstraße 60 | E9: Rg-Nr.: | G9: 60431-2024-002
E10: Leistungsdatum:* | G10: =+G7 -> 45420
A11: 60488 Frankfurt | E11: IBAN: | F11: DE13 50070024 0 4092862 00
E12: BIC: | F12: DEUTDEDBFRA
A18: Rechnung über Honorare
A22: Für die nachfolgend aufgeführten Leistungen erlaube ich mir, nach der Steuerberatervergütungs-
A23: verordnung wie folgt abzurechnen:
A24: Leistung | E24: Wert/ | F24: Tabelle | G24: Geb.-Satz/ | H24: Gebühr
A25: §§ | E25: Std.-Satz | G25: Stunden
A26: 24 | B26: Umsatzsteuererklärung | C26: 2022 | E26: =+(101666+360+31)/10 -> 10205.7 | F26: A | G26: 0.3 | H26: =G26*618 -> 185.4
A28: 24 | B28: Gewerbesteuererklärung (Überarberitung) | C28: =+C26 -> 2022 | E28: 19147.6 | F28: A | G28: 0.3 | H28: =+G28*759 -> 227.7
A30: 25 | B30: Einnahmenüberschußrechnung | C30: =+C28 -> 2022 | E30: 121614.71 | F30: B | G30: 2.5 | H30: =+G30*399 -> 997.5
A32: 16 | B32: Auslagenersatz für Post- und | E32: =SUM(H26:H30)*0.12 -> 169.272 | H32: 0
B33: Telekommunikation für o.g. Posten
A35: 16 | B35: Auslagenersatz nachgewiesener Kosten: DATEV-Archiv-CD
B36: gemäß beigefügter Rg-Kopie (Rg 498/2024 v. Haas u. Kollegen GmbH)** | H36: 90
A37: * soweit nicht gesondert anders ausgewiesen | E37: Gesamt | H37: =SUM(H26:H36) -> 1500.6
A38: ** Leistungszeitraum siehe dort | E38: USt 19% | H38: =+H37*0.19 -> 285.114
E39: Rechnungsendbetrag | H39: =SUM(H37:H38) -> 1785.714
A41: Bitte überweisen Sie den Rechnungsbetrag ohne Abzüge auf das angegebene Konto.
A49: Steuernummer: 012 801 35159

Sheet ESt 2022
A5: Hartmut Ahting, Steuerberater, Heerstrasse 50, 60488 Frankfurt
A7: Herr und Frau | E7: Rg-Datum: | G7: 45420
A8: Roger u. Anita Detroy | E8: Kunden-Nr.: | H8: 60431
A9: Tarnowitzstr. 59 | E9: Rg-Nr.: | G9: 60431-2024-003
E10: Leistungsdatum: | G10: =+G7 -> 45420
A11: 65933 Frankfurt | E11: IBAN: | F11: DE13 50070024 0 4092862 00
E12: BIC: | F12: DEUTDEDBFRA
A17: Rechnung über Honorare
A20: Für die nachfolgend aufgeführten Leistungen erlaube ich mir, nach der Steuerberatervergütungs-
A21: verordnung wie folgt abzurechnen:
A22: Leistung | E22: Wert/ | F22: Tabelle | G22: Geb.-Satz/ | H22: Gebühr
A23: §§ | E23: Std.-Satz | G23: Stunden
A24: 24 | B24: Einkommensteuererklärung ohne Ermittlung | E24: 31791 | F24: A | G24: 0.1 | H24: =+G24*977 -> 97.7
B25: der einzelnen Einkünfte für | C25: 2022
A27: 27 | B27: Überschußermittlung bei den sonstigen Einkünften | E27: 10548 | F27: A | G27: 0.1 | H27: =+G27*608 -> 60.8
B28: hier: aus Renten (Herr Detroy) | C28: =+C25 -> 2022
A30: 27 | B30: Überschußermittlung bei den sonstigen Einkünften | E30: 8000 | F30: A | G30: 0.1 | H30: =+G30*485 -> 48.5
B31: hier: aus Renten (Frau Detroy) | C31: =+C28 -> 2022
A33: 16 | B33: Auslagenersatz für Post- und | E33: =SUM(H24:H30)*0.2 -> 41.4 | H33: 20
B34: Telekommunikation (pauschal)
E38: Gesamt | H38: =SUM(H24:H35) -> 227 | J38: =+H38+'EÜR 2022'!H37 -> 1727.6
E39: USt 19% | H39: =+H38*0.19 -> 43.13
E40: Rechnungsendbetrag | H40: =SUM(H38:H39) -> 270.13
A42: Bitte überweisen Sie den Rechnungsbetrag ohne Abzüge auf das angegebene Konto.
A49: Steuernummer: 012 801 35159

Sheet Fibu I-2024
A5: Hartmut Ahting, Steuerberater, Heerstrasse 50, 60488 Frankfurt
A7: Herr | E7: Rg-Datum: | G7: 45425
A8: Roger Detroy | E8: Kunden-Nr.: | H8: 60431
A9: Heerstraße 60 | E9: Rg-Nr.: | G9: 60431-2024-004
E10: Leistungsdatum: | G10: 45412
A11: 60488 Frankfurt | E11: IBAN: | F11: DE13 50070024 0 4092862 00
E12: BIC: | F12: DEUTDEDBFRA
A16: Rechnung über Honorare
A19: Für die nachfolgend aufgeführten Leistungen erlaube ich mir, in Übereinstimmung mit der
A20: Steuerberatervergütungsverordnung wie folgt abzurechnen:
A22: Leistung | E22: Gegenstands- | F22: Tabelle | G22: Geb.- | H22: Gebühr
A23: §§ | C23: am/in | E23: wert | G23: Satz
A24: 33 | B24: Buchführung einschl. Kontieren der Belege für:
B25: 45323 | E25: =ROUNDDOWN((23974.96/2)/(128664.92/12)*128664.92/1000,)*1000 -> 143000 | F25: C | G25: 7 | H25: =G25/10*217 -> 151.9
B26: 45352 | E26: =+E25 -> 143000 | F26: C | G26: 7 | H26: =G26/10*217 -> 151.9
A29: 16 | B29: Auslagenersatz für Post- und | E29: =SUM(H24:H28)*0.2 -> 60.76 | G29: =+E29*0.2 -> 12.152 | H29: 40
B30: Telekommunikation
E31: Gesamt | H31: =SUM(H24:H30) -> 343.8
E32: USt 19% | H32: =+H31*0.19 -> 65.322
E33: Rechnungsendbetrag | H33: =SUM(H31:H32) -> 409.122
A35: Bitte überweisen Sie den Betrag ohne Abzüge auf die angegebene Bankverbindung.
A49: USt-ID: DE212505221

Sheet DRV-Prüfung 20-23
A5: Hartmut Ahting, Steuerberater, Heerstrasse 50, 60488 Frankfurt
A7: Herr | E7: Rg-Datum: | G7: 45474
A8: Roger Detroy | E8: Kunden-Nr.: | H8: 60431
A9: Heerstraße 60 | E9: Rg-Nr.: | G9: 60431-2024-005
E10: Leistungsdatum: | G10: =+G7 -> 45474
A11: 60488 Frankfurt | E11: IBAN: | F11: DE13 50070024 0 4092862 00
E12: BIC: | F12: DEUTDEDBFRA
A16: Rechnung über Honorare
A19: Für die nachfolgend aufgeführten Leistungen erlaube ich mir, in Übereinstimmung mit der
A20: Steuerberatervergütungsverordnung wie folgt abzurechnen:
A22: Leistung | E22: Gegenstands- | F22: Tabelle | G22: Geb.- | H22: Gebühr
A23: §§ | C23: am/in: | E23: wert | G23: satz/Std.
A24: 29 | B24: Teilnahme an der Sozialversicherungsprüfug | E24: 120 | F24: Zeitgeb. | G24: 4.5 | H24: =+G24*E24 -> 540
B25: durch die DRV für 2020-2023
B26: - Vorbereitung der Prüfung und Zusammen-
B27: stellung von Unterlagen/Bereitstellung von DATEV-Lohnarchiv-CD-Daten
B28: am 08.05.2024 und am 20.06.2024
B29: - Abschluß der Prüfung durch Prüfung der Prüfungs-
B30: schlußmitteilung am 01.07.2024
A33: 16 | B33: Auslagenersatz für Post- und | E33: =SUM(H24:H32)*0.2 -> 108 | H33: 10
B34: Telekommunikation
E35: Gesamt | H35: =SUM(H24:H34) -> 550
E36: USt 19% | H36: =+H35*0.19 -> 104.5
E37: Rechnungsendbetrag | H37: =+H35+H36 -> 654.5
A38: Bitte überweisen Sie den Betrag ohne Abzüge innerhalb von 14 Tagen auf das angegebene Konto.
A48: USt-ID: DE212505221

Sheet Lohn I+II-2024
A5: Hartmut Ahting, Steuerberater, Heerstrasse 50, 60488 Frankfurt
A7: Herr | E7: Rg-Datum: | G7: 45540
A8: Roger Detroy | E8: Kunden-Nr.: | H8: 60431
A9: Heerstraße 60 | E9: Rg-Nr.: | G9: 60431-2024-006
E10: Leistungsdatum: | G10: siehe Einzelpos. | L10: 34 | M10: Hilfeleistung bei sonstigen Tätigkeiten der
A11: 60488 Frankfurt | E11: IBAN: | F11: DE13 50070024 0 4092862 00 | M11: Lohnbuchführung
E12: BIC: | F12: DEUTDEDBFRA | M12: - LFZ-Anträge - Lina Haas am 27.02.; 15.03. u | P12: 50 | Q12: Zeitgeb. | R12: 0.5 | S12: =+R12*P12 -> 25
M13: 22.03.20178
A16: Rechnung über Honorare
A19: Für die nachfolgend aufgeführten Leistungen erlaube ich mir, in Übereinstimmung mit der
A20: Steuerberatervergütungsverordnung wie folgt abzurechnen:
A22: Leistung | E22: Gegenstands- | F22: Tabelle | G22: Geb.- | H22: Gebühr
A23: §§ | C23: am/in: | E23: wert / AN | G23: Satz
A24: 34 | B24: Löhne/Gehälter 03/2024 | C24: 45379
A25: - | B25: Einrichten von Lohnkonten (Severin) | E25: 18 | G25: 2 | H25: =+G25*E25 -> 36
A26: - | B26: Lohnabrechnungen inkl. Sozialversicherungsmeldungen | E26: 28 | G26: 2 | H26: =+G26*E26 -> 56
A28: 34 | B28: Löhne/Gehälter 04/2024 | C28: 45401
A29: - | B29: Lohnabrechnungen inkl. Sozialversicherungsmeldungen | E29: 28 | G29: 2 | H29: =+G29*E29 -> 56
A31: 34 | B31: Löhne/Gehälter 05/2024 | C31: 45434
A32: - | B32: Lohnabrechnungen inkl. Sozialversicherungsmeldungen | E32: 28 | G32: 2 | H32: =+G32*E32 -> 56
A34: 34 | B34: Löhne/Gehälter 06/2024 | C34: 45461
A35: - | B35: Lohnabrechnungen inkl. Sozialversicherungsmeldungen | E35: 28 | G35: 2 | H35: =+G35*E35 -> 56
A38: 16 | B38: Auslagenersatz für Post- und | C38: I+II/2024 | E38: =SUM(H24:H37) -> 260 | G38: =+E38*0.2 -> 52 | H38: =+G38 -> 52
B39: Telekommunikation
E40: Gesamt | H40: =SUM(H24:H39) -> 312
E41: USt 19% | H41: =+H40*0.19 -> 59.28
E42: Rechnungsendbetrag | H42: =SUM(H40:H41) -> 371.28
A44: Bitte überweisen Sie den Betrag ohne Abzüge auf die angegebene Bankverbindung.
A52: Steuernummer: 014 801 32096

Sheet Fibu II-2024
A5: Hartmut Ahting, Steuerberater, Heerstrasse 50, 60488 Frankfurt
A7: Herr | E7: Rg-Datum: | G7: 45540
A8: Roger Detroy | E8: Kunden-Nr.: | H8: 60431
A9: Heerstraße 60 | E9: Rg-Nr.: | G9: 60431-2024-007
E10: Leistungsdatum: | G10: siehe Einzelposition
A11: 60488 Frankfurt | E11: IBAN: | F11: DE13 50070024 0 4092862 00
E12: BIC: | F12: DEUTDEDBFRA
A16: Rechnung über Honorare
A19: Für die nachfolgend aufgeführten Leistungen erlaube ich mir, in Übereinstimmung mit der
A20: Steuerberatervergütungsverordnung wie folgt abzurechnen:
A22: Leistung | E22: Gegenstands- | F22: Tabelle | G22: Geb.- | H22: Gebühr
A23: §§ | C23: am/in | E23: wert | G23: Satz
A24: 33 | B24: Buchführung einschl. Kontieren der Belege für:
B25: 45383 | C25: 45475 | E25: =ROUNDDOWN((23974.96/2)/(128664.92/12)*128664.92/1000,)*1000 -> 143000 | F25: C | G25: 7 | H25: =G25/10*217 -> 151.9
B26: 45413 | C26: 45510 | E26: =+E25 -> 143000 | F26: C | G26: 7 | H26: =G26/10*217 -> 151.9
B27: 45444 | C27: =+C26 -> 45510 | E27: =+E26 -> 143000 | F27: C | G27: 7 | H27: =G27/10*217 -> 151.9
A29: 16 | B29: Auslagenersatz für Post- und | C29: 02.07.-06.08.2024 | H29: 40
B30: Telekommunikation
E31: Gesamt | H31: =SUM(H24:H30) -> 495.7
E32: USt 19% | H32: =+H31*0.19 -> 94.183
E33: Rechnungsendbetrag | H33: =SUM(H31:H32) -> 589.883
A35: Bitte überweisen Sie den Betrag ohne Abzüge auf die angegebene Bankverbindung.
A49: Steuernummer: 014 801 32096

Sheet Lohn III-2024
A5: Hartmut Ahting, Steuerberater, Heerstrasse 50, 60488 Frankfurt
A7: Herr | E7: Rg-Datum: | G7: 45593
A8: Roger Detroy | E8: Kunden-Nr.: | H8: 60431
A9: Heerstraße 60 | E9: Rg-Nr.: | G9: 60431-2024-008
E10: Leistungsdatum: | G10: siehe Einzelpos. | L10: 34 | M10: Hilfeleistung bei sonstigen Tätigkeiten der
A11: 60488 Frankfurt | E11: IBAN: | F11: DE13 50070024 0 4092862 00 | M11: Lohnbuchführung
E12: BIC: | F12: DEUTDEDBFRA | M12: - LFZ-Anträge - Lina Haas am 27.02.; 15.03. u | P12: 50 | Q12: Zeitgeb. | R12: 0.5 | S12: =+R12*P12 -> 25
M13: 22.03.20178
M16: - | N16: Einrichten von Lohnkonten (Severin) | Q16: 18 | S16: 2 | T16: =+S16*Q16 -> 36
A17: Rechnung über Honorare
A20: Für die nachfolgend aufgeführten Leistungen erlaube ich mir, in Übereinstimmung mit der
A21: Steuerberatervergütungsverordnung wie folgt abzurechnen:
A23: Leistung | E23: Gegenstands- | F23: Tabelle | G23: Geb.- | H23: Gebühr
A24: §§ | C24: am/in: | E24: wert / AN | G24: Satz
A25: 34 | B25: Löhne/Gehälter 07/2024 | C25: 45497
A26: - | B26: Lohnabrechnungen inkl. Sozialversicherungsmeldungen | E26: 28 | G26: 2 | H26: =+G26*E26 -> 56
A28: 34 | B28: Löhne/Gehälter 08/2024 | C28: 45518
A29: - | B29: Lohnabrechnungen inkl. Sozialversicherungsmeldungen | E29: 28 | G29: 2 | H29: =+G29*E29 -> 56
A31: 34 | B31: Löhne/Gehälter 09/2024 | C31: 45555
A32: - | B32: Lohnabrechnungen inkl. Sozialversicherungsmeldungen | E32: 28 | G32: 2 | H32: =+G32*E32 -> 56
A38: 16 | B38: Auslagenersatz für Post- und | C38: III/2024 | E38: =SUM(H25:H37) -> 168 | G38: =+E38*0.2 -> 33.6 | H38: =+G38 -> 33.6
B39: Telekommunikation
E40: Gesamt | H40: =SUM(H25:H39) -> 201.6
E41: USt 19% | H41: =+H40*0.19 -> 38.304
E42: Rechnungsendbetrag | H42: =SUM(H40:H41) -> 239.904
A44: Bitte überweisen Sie den Betrag ohne Abzüge auf die angegebene Bankverbindung.
A52: Steuernummer: 014 801 32096

Sheet Fibu III-2024
A5: Hartmut Ahting, Steuerberater, Heerstrasse 50, 60488 Frankfurt
A7: Herr | E7: Rg-Datum: | G7: 45593
A8: Roger Detroy | E8: Kunden-Nr.: | H8: 60431
A9: Heerstraße 60 | E9: Rg-Nr.: | G9: 60431-2024-009
E10: Leistungsdatum: | G10: siehe Einzelpos.
A11: 60488 Frankfurt | E11: IBAN: | F11: DE13 50070024 0 4092862 00
E12: BIC: | F12: DEUTDEDBFRA
A16: Rechnung über Honorare
A19: Für die nachfolgend aufgeführten Leistungen erlaube ich mir, in Übereinstimmung mit der
A20: Steuerberatervergütungsverordnung wie folgt abzurechnen:
A22: Leistung | E22: Gegenstands- | F22: Tabelle | G22: Geb.- | H22: Gebühr
A23: §§ | C23: am/in | E23: wert | G23: Satz
A24: 33 | B24: Buchführung einschl. Kontieren der Belege für:
B25: 45474 | C25: 45538 | E25: =ROUNDDOWN((23974.96/2)/(128664.92/12)*128664.92/1000,)*1000 -> 143000 | F25: C | G25: 7 | H25: =G25/10*217 -> 151.9
B26: 45505 | C26: 45565 | E26: =+E25 -> 143000 | F26: C | G26: 7 | H26: =G26/10*217 -> 151.9
B27: 45536 | C27: 45590 | E27: =+E26 -> 143000 | F27: C | G27: 7 | H27: =G27/10*217 -> 151.9
B28: Januar 2024 (Nachbuchung) | C28: =+C27 -> 45590 | E28: =+E27 -> 143000 | F28: C | G28: 7 | H28: =G28/10*217 -> 151.9
A30: 16 | B30: Auslagenersatz für Post- und | C30: 03.09.-25.10.2024 | H30: 80
B31: Telekommunikation
E32: Gesamt | H32: =SUM(H24:H31) -> 687.6
E33: USt 19% | H33: =+H32*0.19 -> 130.644
E34: Rechnungsendbetrag | H34: =SUM(H32:H33) -> 818.244
A36: Bitte überweisen Sie den Betrag ohne Abzüge auf die angegebene Bankverbindung.
A49: Steuernummer: 014 801 32096

Sheet Fibu IV-2024
A5: Hartmut Ahting, Steuerberater, Heerstrasse 50, 60488 Frankfurt
A7: Herr | E7: Rg-Datum: | G7: 45712
A8: Roger Detroy | E8: Kunden-Nr.: | H8: 60431
A9: Heerstraße 60 | E9: Rg-Nr.: | G9: 60431-2025-001
E10: Leistungsdatum: | G10: siehe Einzelpos.
A11: 60488 Frankfurt | E11: IBAN: | F11: DE13 50070024 0 4092862 00
E12: BIC: | F12: DEUTDEDBFRA
A16: Rechnung über Honorare
A19: Für die nachfolgend aufgeführten Leistungen erlaube ich mir, in Übereinstimmung mit der
A20: Steuerberatervergütungsverordnung wie folgt abzurechnen:
A22: Leistung | E22: Gegenstands- | F22: Tabelle | G22: Geb.- | H22: Gebühr
A23: §§ | C23: am/in | E23: wert | G23: Satz
A24: 33 | B24: Buchführung einschl. Kontieren der Belege für:
B25: 45566 | C25: 45629 | E25: =ROUNDDOWN((23974.96/2)/(128664.92/12)*128664.92/1000,)*1000 -> 143000 | F25: C | G25: 8 | H25: =G25/10*217 -> 173.6
B26: 45597 | C26: 45659 | E26: =+E25 -> 143000 | F26: C | G26: =+G25 -> 8 | H26: =G26/10*217 -> 173.6
B27: 45627 | C27: 45708 | E27: =+E26 -> 143000 | F27: C | G27: =+G26 -> 8 | H27: =G27/10*217 -> 173.6
A30: 16 | B30: Auslagenersatz für Post- und | C30: 03.12.24-20.02.2025 | H30: 80
B31: Telekommunikation
E32: Gesamt | H32: =SUM(H24:H31) -> 600.8
E33: USt 19% | H33: =+H32*0.19 -> 114.152
E34: Rechnungsendbetrag | H34: =SUM(H32:H33) -> 714.952
A36: Bitte überweisen Sie den Betrag ohne Abzüge auf die angegebene Bankverbindung.
A49: Steuernummer: 014 801 32096

Sheet Lohn I+II-2025
A5: Hartmut Ahting, Steuerberater, Heerstrasse 50, 60488 Frankfurt
A7: Herr | E7: Rg-Datum: | G7: 45875
A8: Roger Detroy | E8: Kunden-Nr.: | H8: 60431
A9: Heerstraße 60 | E9: Rg-Nr.: | G9: 60431-2025-005
E10: Leistungsdatum: | G10: siehe Einzelpos. | L10: 34 | M10: Hilfeleistung bei sonstigen Tätigkeiten der
A11: 60488 Frankfurt | E11: IBAN: | F11: DE13 50070024 0 4092862 00 | M11: Lohnbuchführung
E12: BIC: | F12: DEUTDEDBFRA | M12: - LFZ-Anträge - Lina Haas am 27.02.; 15.03. u | P12: 50 | Q12: Zeitgeb. | R12: 0.5 | S12: =+R12*P12 -> 25
M13: 22.03.20178
M15: - | N15: Einrichten von Lohnkonten (Severin) | Q15: 18 | S15: 2 | T15: =+S15*Q15 -> 36
A16: Rechnung über Honorare
A19: Für die nachfolgend aufgeführten Leistungen erlaube ich mir, in Übereinstimmung mit der
A20: Steuerberatervergütungsverordnung wie folgt abzurechnen:
A22: Leistung | E22: Gegenstands- | F22: Tabelle | G22: Geb.- | H22: Gebühr
A23: §§ | C23: am/in: | E23: wert / AN | G23: Satz
A24: 34 | B24: Löhne/Gehälter
A25: - | B25: Lohnabrechnungen inkl. Sozialversicherungsmeldungen für
B26: 45658 | C26: 45681 | E26: 28 | G26: 2 | H26: =+G26*E26 -> 56
B27: 45689 | C27: 45712 | E27: 28 | G27: 2 | H27: =+G27*E27 -> 56
B28: 45717 | C28: 45735 | E28: 28 | G28: 2 | H28: =+G28*E28 -> 56
B29: 45748 | C29: 45770 | E29: 28 | G29: 2 | H29: =+G29*E29 -> 56
B30: 45778 | C30: 45798 | E30: 28 | G30: 2 | H30: =+G30*E30 -> 56
B31: 45809 | C31: 45826 | E31: 28 | G31: 2 | H31: =+G31*E31 -> 56
A35: 16 | B35: Auslagenersatz für Post- und | C35: I+II/2025 | E35: =SUM(H24:H34) -> 336 | G35: =+E35*0.2 -> 67.2 | H35: =+G35 -> 67.2
B36: Telekommunikation
E37: Gesamt | H37: =SUM(H24:H36) -> 403.2
E38: USt 19% | H38: =+H37*0.19 -> 76.608
E39: Rechnungsendbetrag | H39: =SUM(H37:H38) -> 479.808
A41: Bitte überweisen Sie den Betrag ohne Abzüge auf die angegebene Bankverbindung.
A49: Steuernummer: 014 801 32096

Sheet Lohn IV-2024
A5: Hartmut Ahting, Steuerberater, Heerstrasse 50, 60488 Frankfurt
A7: Herr | E7: Rg-Datum: | G7: 45712
A8: Roger Detroy | E8: Kunden-Nr.: | H8: 60431
A9: Heerstraße 60 | E9: Rg-Nr.: | G9: 60431-2025-002
E10: Leistungsdatum: | G10: siehe Einzelpos.
A11: 60488 Frankfurt | E11: IBAN: | F11: DE13 50070024 0 4092862 00
E12: BIC: | F12: DEUTDEDBFRA
A17: Rechnung über Honorare
A20: Für die nachfolgend aufgeführten Leistungen erlaube ich mir, in Übereinstimmung mit der
A21: Steuerberatervergütungsverordnung wie folgt abzurechnen:
A23: Leistung | E23: Gegenstands- | F23: Tabelle | G23: Geb.- | H23: Gebühr
A24: §§ | C24: am/in: | E24: wert / AN | G24: Satz
A25: 34 | B25: Löhne/Gehälter 10/2024 | C25: 45588
A26: - | B26: Lohnabrechnungen inkl. Sozialversicherungsmeldungen | E26: 28 | G26: 2 | H26: =+G26*E26 -> 56
A28: 34 | B28: Löhne/Gehälter 11/2024 | C28: 45618
A29: - | B29: Lohnabrechnungen inkl. Sozialversicherungsmeldungen | E29: 28 | G29: 2 | H29: =+G29*E29 -> 56
A31: 34 | B31: Löhne/Gehälter 12/2024 | C31: 45644
A32: - | B32: Lohnabrechnungen inkl. Sozialversicherungsmeldungen | E32: 28 | G32: 2 | H32: =+G32*E32 -> 56
A38: 16 | B38: Auslagenersatz für Post- und | C38: IV/2024 | E38: =SUM(H25:H37) -> 168 | G38: =+E38*0.2 -> 33.6 | H38: =+G38 -> 33.6
B39: Telekommunikation
E40: Gesamt | H40: =SUM(H25:H39) -> 201.6
E41: USt 19% | H41: =+H40*0.19 -> 38.304
E42: Rechnungsendbetrag | H42: =SUM(H40:H41) -> 239.904
A44: Bitte überweisen Sie den Betrag ohne Abzüge auf die angegebene Bankverbindung.
A52: Steuernummer: 014 801 32096

Sheet EÜR 2023
A5: Hartmut Ahting, Steuerberater, Heerstrasse 50, 60488 Frankfurt
A7: Herr | E7: Rg-Datum: | G7: 45720
A8: Roger Detroy | E8: Kunden-Nr.: | H8: 60431
A9: Heerstraße 60 | E9: Rg-Nr.: | G9: 60431-2025-003
E10: Leistungsdatum:* | G10: =+G7 -> 45720
A11: 60488 Frankfurt | E11: IBAN: | F11: DE13 50070024 0 4092862 00
E12: BIC: | F12: DEUTDEDBFRA
A18: Rechnung über Honorare
A22: Für die nachfolgend aufgeführten Leistungen erlaube ich mir, nach der Steuerberatervergütungs-
A23: verordnung wie folgt abzurechnen:
A24: Leistung | E24: Wert/ | F24: Tabelle | G24: Geb.-Satz/ | H24: Gebühr
A25: §§ | E25: Std.-Satz | G25: Stunden
A26: 24 | B26: Umsatzsteuererklärung | C26: 2023 | E26: =(107742+360)/10 -> 10810.2 | F26: A | G26: 0.3 | H26: =G26*618 -> 185.4
A28: 24 | B28: Gewerbesteuererklärung | C28: =+C26 -> 2023 | E28: 28775 | F28: A | G28: 0.3 | H28: =+G28*892 -> 267.6
A30: 25 | B30: Einnahmenüberschußrechnung | C30: =+C28 -> 2023 | E30: 128724.92 | F30: B | G30: 2.5 | H30: =+G30*444 -> 1110
A32: 16 | B32: Auslagenersatz für Post- und | E32: =SUM(H26:H30)*0.12 -> 187.56 | H32: 0
B33: Telekommunikation für o.g. Posten
A35: 16 | B35: Auslagenersatz nachgewiesener Kosten: DATEV-Archiv-CD
B36: gemäß beigefügter Rg-Kopie (Rg 498/2024 v. Haas u. Kollegen GmbH)** | H36: 90
A37: * soweit nicht gesondert anders ausgewiesen | E37: Gesamt | H37: =SUM(H26:H36) -> 1653
A38: ** Leistungszeitraum siehe dort | E38: USt 19% | H38: =+H37*0.19 -> 314.07
E39: Rechnungsendbetrag | H39: =SUM(H37:H38) -> 1967.07
A41: Bitte überweisen Sie den Rechnungsbetrag ohne Abzüge auf das angegebene Konto.
A49: Steuernummer: 014 801 32096

Sheet ESt 2023
A5: Hartmut Ahting, Steuerberater, Heerstrasse 50, 60488 Frankfurt
A7: Herr und Frau | E7: Rg-Datum: | G7: 45420
A8: Roger u. Anita Detroy | E8: Kunden-Nr.: | H8: 60431
A9: Tarnowitzstr. 59 | E9: Rg-Nr.: | G9: 60431-2025-004
E10: Leistungsdatum: | G10: =+G7 -> 45420
A11: 65933 Frankfurt | E11: IBAN: | F11: DE13 50070024 0 4092862 00
E12: BIC: | F12: DEUTDEDBFRA
A17: Rechnung über Honorare
A20: Für die nachfolgend aufgeführten Leistungen erlaube ich mir, nach der Steuerberatervergütungs-
A21: verordnung wie folgt abzurechnen:
A22: Leistung | E22: Wert/ | F22: Tabelle | G22: Geb.-Satz/ | H22: Gebühr
A23: §§ | E23: Std.-Satz | G23: Stunden
A24: 24 | B24: Einkommensteuererklärung ohne Ermittlung | E24: 41280 | F24: A | G24: 0.1 | H24: =+G24*1146 -> 114.6
B25: der einzelnen Einkünfte für | C25: 2023
A27: 27 | B27: Überschußermittlung bei den sonstigen Einkünften | E27: 11060 | F27: A | G27: 0.1 | H27: =+G27*608 -> 60.8
B28: hier: aus Renten (Herr Detroy) | C28: =+C25 -> 2023
A30: 27 | B30: Überschußermittlung bei den sonstigen Einkünften | E30: 8000 | F30: A | G30: 0.1 | H30: =+G30*485 -> 48.5
B31: hier: aus Renten (Frau Detroy) | C31: =+C28 -> 2023
A33: 16 | B33: Auslagenersatz für Post- und | E33: =SUM(H24:H30)*0.2 -> 44.78 | H33: 20
B34: Telekommunikation (pauschal)
E38: Gesamt | H38: =SUM(H24:H35) -> 243.9 | J38: =+H38+'EÜR 2023'!H37 -> 1896.9
E39: USt 19% | H39: =+H38*0.19 -> 46.341
E40: Rechnungsendbetrag | H40: =SUM(H38:H39) -> 290.241
A42: Bitte überweisen Sie den Rechnungsbetrag ohne Abzüge auf das angegebene Konto.
A51: Steuernummer: 014 801 32096

Sheet Fibu I-2025
A5: Hartmut Ahting, Steuerberater, Heerstrasse 50, 60488 Frankfurt
A7: Herr | E7: Rg-Datum: | G7: 45875
A8: Roger Detroy | E8: Kunden-Nr.: | H8: 60431
A9: Heerstraße 60 | E9: Rg-Nr.: | G9: 60431-2025-006
E10: Leistungsdatum: | G10: siehe Einzelpos.
A11: 60488 Frankfurt | E11: IBAN: | F11: DE13 50070024 0 4092862 00
E12: BIC: | F12: DEUTDEDBFRA
A16: Rechnung über Honorare
A19: Für die nachfolgend aufgeführten Leistungen erlaube ich mir, in Übereinstimmung mit der
A20: Steuerberatervergütungsverordnung wie folgt abzurechnen:
A22: Leistung | E22: Gegenstands- | F22: Tabelle | G22: Geb.- | H22: Gebühr
A23: §§ | C23: am/in | E23: wert | G23: Satz
A24: 33 | B24: Buchführung einschl. Kontieren der Belege für:
B25: 45658 | C25: 45708 | E25: =ROUNDDOWN((23974.96/2)/(128664.92/12)*128664.92/1000,)*1000 -> 143000 | F25: C | G25: 9 | H25: =G25/10*217 -> 195.3
B26: 45689 | C26: 45749 | E26: =+E25 -> 143000 | F26: C | G26: =+G25 -> 9 | H26: =G26/10*217 -> 195.3
B27: 45717 | C27: 45786 | E27: =+E26 -> 143000 | F27: C | G27: =+G26 -> 9 | H27: =G27/10*217 -> 195.3
A30: 16 | B30: Auslagenersatz für Post- und | C30: 20.02.-09.05.2025 | H30: 80
B31: Telekommunikation
E32: Gesamt | H32: =SUM(H24:H31) -> 665.9
E33: USt 19% | H33: =+H32*0.19 -> 126.521
E34: Rechnungsendbetrag | H34: =SUM(H32:H33) -> 792.421
A36: Bitte überweisen Sie den Betrag ohne Abzüge auf die angegebene Bankverbindung.
A49: Steuernummer: 014 801 32096

Sheet Fibu II-2025
A5: Hartmut Ahting, Steuerberater, Heerstrasse 50, 60488 Frankfurt
A7: Herr | E7: Rg-Datum: | G7: 45875
A8: Roger Detroy | E8: Kunden-Nr.: | H8: 60431
A9: Heerstraße 60 | E9: Rg-Nr.: | G9: 60431-2025-007
E10: Leistungsdatum: | G10: siehe Einzelpos.
A11: 60488 Frankfurt | E11: IBAN: | F11: DE13 50070024 0 4092862 00
E12: BIC: | F12: DEUTDEDBFRA
A16: Rechnung über Honorare
A19: Für die nachfolgend aufgeführten Leistungen erlaube ich mir, in Übereinstimmung mit der
A20: Steuerberatervergütungsverordnung wie folgt abzurechnen:
A22: Leistung | E22: Gegenstands- | F22: Tabelle | G22: Geb.- | H22: Gebühr
A23: §§ | C23: am/in | E23: wert | G23: Satz
A24: 33 | B24: Buchführung einschl. Kontieren der Belege für:
B25: 45748 | C25: 45818 | E25: =ROUNDDOWN((23974.96/2)/(128664.92/12)*128664.92/1000,)*1000 -> 143000 | F25: C | G25: 9 | H25: =G25/10*217 -> 195.3
B26: 45778 | C26: 45831 | E26: =+E25 -> 143000 | F26: C | G26: =+G25 -> 9 | H26: =G26/10*217 -> 195.3
B27: 45809 | C27: 45874 | E27: =+E26 -> 143000 | F27: C | G27: =+G26 -> 9 | H27: =G27/10*217 -> 195.3
A30: 16 | B30: Auslagenersatz für Post- und | C30: 10.06.-05.08.2025 | H30: 80
B31: Telekommunikation
E32: Gesamt | H32: =SUM(H24:H31) -> 665.9
E33: USt 19% | H33: =+H32*0.19 -> 126.521
E34: Rechnungsendbetrag | H34: =SUM(H32:H33) -> 792.421
A36: Bitte überweisen Sie den Betrag ohne Abzüge auf die angegebene Bankverbindung.
A49: Steuernummer: 014 801 32096

Sheet Lohn III-2025
A5: Hartmut Ahting, Steuerberater, Heerstrasse 50, 60488 Frankfurt
A7: Herr | E7: Rg-Datum: | G7: 45951
A8: Roger Detroy | E8: Kunden-Nr.: | H8: 60431
A9: Heerstraße 60 | E9: Rg-Nr.: | G9: 60431-2025-008
E10: Leistungsdatum: | G10: siehe Einzelpos. | L10: 34 | M10: Hilfeleistung bei sonstigen Tätigkeiten der
A11: 60488 Frankfurt | E11: IBAN: | F11: DE13 50070024 0 4092862 00 | M11: Lohnbuchführung
E12: BIC: | F12: DEUTDEDBFRA | M12: - LFZ-Anträge - Lina Haas am 27.02.; 15.03. u | P12: 50 | Q12: Zeitgeb. | R12: 0.5 | S12: =+R12*P12 -> 25
M13: 22.03.20178
M15: - | N15: Einrichten von Lohnkonten (Severin) | Q15: 18 | S15: 2 | T15: =+S15*Q15 -> 36
A16: Rechnung über Honorare
A19: Für die nachfolgend aufgeführten Leistungen erlaube ich mir, in Übereinstimmung mit der
A20: Steuerberatervergütungsverordnung wie folgt abzurechnen:
A22: Leistung | E22: Gegenstands- | F22: Tabelle | G22: Geb.- | H22: Gebühr
A23: §§ | C23: am/in: | E23: wert / AN | G23: Satz
A24: 34 | B24: Löhne/Gehälter
A25: - | B25: Lohnabrechnungen inkl. Sozialversicherungsmeldungen für
B26: 45839 | C26: 45860 | E26: 28 | G26: 2 | H26: =+G26*E26 -> 56
B27: 45870 | C27: 45894 | E27: 28 | G27: 2 | H27: =+G27*E27 -> 56
B28: 45901 | C28: 45919 | E28: 28 | G28: 2 | H28: =+G28*E28 -> 56
A35: 16 | B35: Auslagenersatz für Post- und | C35: III/2025 | E35: =SUM(H24:H34) -> 168 | G35: =+E35*0.2 -> 33.6 | H35: =+G35 -> 33.6
B36: Telekommunikation
E37: Gesamt | H37: =SUM(H24:H36) -> 201.6
E38: USt 19% | H38: =+H37*0.19 -> 38.304
E39: Rechnungsendbetrag | H39: =SUM(H37:H38) -> 239.904
A41: Bitte überweisen Sie den Betrag ohne Abzüge auf die angegebene Bankverbindung.
A50: Steuernummer: 014 801 32096

Sheet Fibu III-2025
A5: Hartmut Ahting, Steuerberater, Heerstrasse 50, 60488 Frankfurt
A7: Herr | E7: Rg-Datum: | G7: 45957
A8: Roger Detroy | E8: Kunden-Nr.: | H8: 60431
A9: Heerstraße 60 | E9: Rg-Nr.: | G9: 60431-2025-009
E10: Leistungsdatum: | G10: siehe Einzelpos.
A11: 60488 Frankfurt | E11: IBAN: | F11: DE13 50070024 0 4092862 00
E12: BIC: | F12: DEUTDEDBFRA
A16: Rechnung über Honorare
A19: Für die nachfolgend aufgeführten Leistungen erlaube ich mir, in Übereinstimmung mit der
A20: Steuerberatervergütungsverordnung wie folgt abzurechnen:
A22: Leistung | E22: Gegenstands- | F22: Tabelle | G22: Geb.- | H22: Gebühr
A23: §§ | C23: am/in | E23: wert | G23: Satz
A24: 33 | B24: Buchführung einschl. Kontieren der Belege für:
B25: 45839 | C25: 45909 | E25: =ROUNDDOWN((23974.96/2)/(128664.92/12)*128664.92/1000,)*1000 -> 143000 | F25: C | G25: 10 | H25: =G25/10*217 -> 217
B26: 45870 | C26: 45922 | E26: =+E25 -> 143000 | F26: C | G26: =+G25 -> 10 | H26: =G26/10*217 -> 217
B27: 45901 | C27: 45957 | E27: =+E26 -> 143000 | F27: C | G27: =+G26 -> 10 | H27: =G27/10*217 -> 217
A30: 16 | B30: Auslagenersatz für Post- und | C30: 09.09.-27.10.2025 | H30: 80
B31: Telekommunikation
E32: Gesamt | H32: =SUM(H25:H31) -> 731
E33: USt 19% | H33: =+H32*0.19 -> 138.89
E34: Rechnungsendbetrag | H34: =SUM(H32:H33) -> 869.89
A36: Bitte überweisen Sie den Betrag ohne Abzüge auf die angegebene Bankverbindung.
A49: Steuernummer: 014 801 32096

Sheet EÜR 2024
A5: Hartmut Ahting, Steuerberater, Heerstrasse 50, 60488 Frankfurt
A7: Herr | E7: Rg-Datum: | G7: 45980
A8: Roger Detroy | E8: Kunden-Nr.: | H8: 60431
A9: Heerstraße 60 | E9: Rg-Nr.: | G9: 60431-2025-010
E10: Leistungsdatum:* | G10: =+G7 -> 45980
A11: 60488 Frankfurt | E11: IBAN: | F11: DE13 50070024 0 4092862 00
E12: BIC: | F12: DEUTDEDBFRA
A18: Rechnung über Honorare
A22: Für die nachfolgend aufgeführten Leistungen erlaube ich mir, nach der Steuerberatervergütungs-
A23: verordnung wie folgt abzurechnen:
A24: Leistung | E24: Wert/ | F24: Tabelle | G24: Geb.-Satz/ | H24: Gebühr
A25: §§ | E25: Std.-Satz | G25: Stunden
A26: 24 | B26: Umsatzsteuererklärung | C26: 2024 | E26: =(114379+360)/10 -> 11473.9 | F26: A | G26: 0.3 | H26: =G26*655 -> 196.5
A28: 24 | B28: Gewerbesteuererklärung | C28: =+C26 -> 2024 | E28: 20153 | F28: A | G28: 0.3 | H28: =+G28*805 -> 241.5
A30: 25 | B30: Einnahmenüberschußrechnung | C30: =+C28 -> 2024 | E30: 136812.33 | F30: B | G30: 2.7 | H30: =+G30*471 -> 1271.7
A32: 16 | B32: Auslagenersatz für Post- und | E32: =SUM(H26:H30)*0.12 -> 205.164 | H32: 0
B33: Telekommunikation für o.g. Posten
A35: 16 | B35: Auslagenersatz für Post- und | H35: 20
B36: Telekommunikation
A37: * soweit nicht gesondert anders ausgewiesen | E37: Gesamt | H37: =SUM(H26:H36) -> 1729.7 | J37: =+'ESt 2024'!H38+'EÜR 2024'!H37 -> 1970.2 | K37: =+'ESt 2023'!H38+'EÜR 2023'!H37 -> 1896.9
A38: ** Leistungszeitraum siehe dort | E38: USt 19% | H38: =+H37*0.19 -> 328.643
E39: Rechnungsendbetrag | H39: =SUM(H37:H38) -> 2058.343
A41: Bitte überweisen Sie den Rechnungsbetrag ohne Abzüge auf das angegebene Konto.
A49: Steuernummer: 014 801 32096

Sheet ESt 2024
A5: Hartmut Ahting, Steuerberater, Heerstrasse 50, 60488 Frankfurt
A7: Herr und Frau | E7: Rg-Datum: | G7: 45980
A8: Roger u. Anita Detroy | E8: Kunden-Nr.: | H8: 60431
A9: Tarnowitzstr. 59 | E9: Rg-Nr.: | G9: 60431-2025-011
E10: Leistungsdatum: | G10: =+G7 -> 45980
A11: 65933 Frankfurt | E11: IBAN: | F11: DE13 50070024 0 4092862 00
E12: BIC: | F12: DEUTDEDBFRA
A17: Rechnung über Honorare
A20: Für die nachfolgend aufgeführten Leistungen erlaube ich mir, nach der Steuerberatervergütungs-
A21: verordnung wie folgt abzurechnen:
A22: Leistung | E22: Wert/ | F22: Tabelle | G22: Geb.-Satz/ | H22: Gebühr
A23: §§ | E23: Std.-Satz | G23: Stunden
A24: 24 | B24: Einkommensteuererklärung ohne Ermittlung | E24: 32813 | F24: A | G24: 0.1 | H24: =+G24*1036 -> 103.6
B25: der einzelnen Einkünfte für | C25: 2024
A27: 27 | B27: Überschußermittlung bei den sonstigen Einkünften | E27: 11556 | F27: A | G27: 0.1 | H27: =+G27*655 -> 65.5
B28: hier: aus Renten (Herr Detroy) | C28: =+C25 -> 2024
A30: 27 | B30: Überschußermittlung bei den sonstigen Einkünften | E30: 8000 | F30: A | G30: 0.1 | H30: =+G30*514 -> 51.4
B31: hier: aus Renten (Frau Detroy) | C31: =+C28 -> 2024
A33: 16 | B33: Auslagenersatz für Post- und | E33: =SUM(H24:H30)*0.2 -> 44.1 | H33: 20
B34: Telekommunikation (pauschal)
E38: Gesamt | H38: =SUM(H24:H35) -> 240.5 | J38: =+H38+'EÜR 2023'!H37 -> 1893.5
E39: USt 19% | H39: =+H38*0.19 -> 45.695
E40: Rechnungsendbetrag | H40: =SUM(H38:H39) -> 286.195
A42: Bitte überweisen Sie den Rechnungsbetrag ohne Abzüge auf das angegebene Konto.
A51: Steuernummer: 014 801 32096

Sheet Lohn IV-2025
A5: Hartmut Ahting, Steuerberater, Heerstrasse 50, 60488 Frankfurt
A7: Herr | E7: Rg-Datum: | G7: 46091
A8: Roger Detroy | E8: Kunden-Nr.: | H8: 60431
A9: Heerstraße 60 | E9: Rg-Nr.: | G9: 60431-2026-001
E10: Leistungszeitraum: | G10: IV. Vj. 2025 | L10: 34 | M10: Hilfeleistung bei sonstigen Tätigkeiten der
A11: 60488 Frankfurt | E11: IBAN: | F11: DE13 50070024 0 4092862 00 | M11: Lohnbuchführung
E12: BIC: | F12: DEUTDEDBFRA | M12: - LFZ-Anträge - Lina Haas am 27.02.; 15.03. u | P12: 50 | Q12: Zeitgeb. | R12: 0.5 | S12: =+R12*P12 -> 25
M13: 22.03.20178
M15: - | N15: Einrichten von Lohnkonten (Severin) | Q15: 18 | S15: 2 | T15: =+S15*Q15 -> 36
A16: Rechnung über Honorare
A19: Für die nachfolgend aufgeführten Leistungen erlaube ich mir, in Übereinstimmung mit der
A20: Steuerberatervergütungsverordnung wie folgt abzurechnen:
A22: Leistung | E22: Gegenstands- | F22: Tabelle | G22: Geb.- | H22: Gebühr
A23: §§ | E23: wert / AN | G23: Satz
A24: 34 | B24: Löhne/Gehälter
A25: - | B25: Lohnabrechnungen inkl. Sozialversicherungsmeldungen für
B26: 45931 | E26: 28 | G26: 1 | H26: =+G26*E26 -> 28
B27: 45962 | E27: 28 | G27: 1 | H27: =+G27*E27 -> 28
B28: 45992 | E28: 28 | G28: 1 | H28: =+G28*E28 -> 28
A35: 16 | B35: Auslagenersatz für Post- und | E35: =SUM(H24:H34) -> 84 | G35: =+E35*0.2 -> 16.8 | H35: =+G35 -> 16.8
B36: Telekommunikation
E37: Gesamt | H37: =SUM(H24:H36) -> 100.8
E38: USt 19% | H38: =+H37*0.19 -> 19.152
E39: Rechnungsendbetrag | H39: =SUM(H37:H38) -> 119.952
A41: Bitte überweisen Sie den Betrag ohne Abzüge auf die angegebene Bankverbindung.
A49: Steuernummer: 014 801 32096

Sheet Fibu IV-2025
A5: Hartmut Ahting, Steuerberater, Heerstrasse 50, 60488 Frankfurt
A7: Herr | E7: Rg-Datum: | G7: 46091
A8: Roger Detroy | E8: Kunden-Nr.: | H8: 60431
A9: Heerstraße 60 | E9: Rg-Nr.: | G9: 60431-2026-002
E10: Leistungszeitraum: | G10: 19.11.2025-10.01.2026
A11: 60488 Frankfurt | E11: IBAN: | F11: DE13 50070024 0 4092862 00
E12: BIC: | F12: DEUTDEDBFRA
A16: Rechnung über Honorare
A19: Für die nachfolgend aufgeführten Leistungen erlaube ich mir, in Übereinstimmung mit der
A20: Steuerberatervergütungsverordnung wie folgt abzurechnen:
A22: Leistung | E22: Gegenstands- | F22: Tabelle | G22: Geb.- | H22: Gebühr
A23: §§ | E23: wert | G23: Satz
A24: 33 | B24: Buchführung einschl. Kontieren der Belege für:
B25: 45931 | E25: 124438 | F25: C | G25: 10 | H25: =G25/10*209 -> 209
B26: 45962 | E26: =+E25 -> 124438 | F26: C | G26: =+G25 -> 10 | H26: =G26/10*209 -> 209
B27: 45992 | E27: =+E26 -> 124438 | F27: C | G27: =+G26 -> 10 | H27: =G27/10*209 -> 209
A30: 16 | B30: Auslagenersatz für Post- und | H30: 80
B31: Telekommunikation
E32: Gesamt | H32: =SUM(H25:H31) -> 707
E33: USt 19% | H33: =+H32*0.19 -> 134.33
E34: Rechnungsendbetrag | H34: =SUM(H32:H33) -> 841.33
A36: Bitte überweisen Sie den Betrag ohne Abzüge auf die angegebene Bankverbindung.
A49: Steuernummer: 014 801 32096
